pytest_param_scope/__init__.py
pytest_param_scope/plugin.py
pytest_param_scope-0.1.1.dist-info/entry_points.txt
pytest_param_scope-0.1.1.dist-info/LICENSE.txt
pytest_param_scope-0.1.1.dist-info/WHEEL
pytest_param_scope-0.1.1.dist-info/METADATA
pytest_param_scope-0.1.1.dist-info/RECORD
