Metadata-Version: 2.1
Name: pytest-param-scope
Version: 0.1.1
Summary: pytest parametrize scope fixture workaround
Author: Brian Okken
Requires-Python: >=3.7
Classifier: License :: OSI Approved :: MIT License
Classifier: Framework :: Pytest
Requires-Dist: pytest
Project-URL: Home, https://github.com/okken/pytest-param-scope
